awesome_ctl/__init__.py
awesome_ctl/agents/__init__.py
awesome_ctl/agents/base_agent.py
awesome_ctl/agents/kubernetes.py
awesome_ctl/alerts/__init__.py
awesome_ctl/alerts/alerter.py
awesome_ctl/alerts/email.py
awesome_ctl/api/__init__.py
awesome_ctl/api/main.py
awesome_ctl/api/models.py
awesome_ctl/api/routes/__init__.py
awesome_ctl/api/routes/healthchecks.py
awesome_ctl/checks/__init__.py
awesome_ctl/checks/base_check.py
awesome_ctl/checks/cpu_check.py
awesome_ctl/checks/dynamic/{__init__.py}
awesome_ctl/config.py
awesome_ctl/llm/__init__.py
awesome_ctl/llm/llm_manager.py
awesome_ctl/llm/providers/__init__.py
awesome_ctl/llm/providers/claude.py
awesome_ctl/llm/providers/gemini.py
awesome_ctl/llm/providers/localai.py
awesome_ctl/llm/providers/openai.py
awesome_ctl/storage/__init__.py
awesome_ctl/storage/influxdb.py
awesome_ctl/ui/package.json
awesome_ctl/ui/public/index.html
awesome_ctl/ui/src/App.tsx
awesome_ctl/ui/src/api/agents.ts
awesome_ctl/ui/src/api/checks.ts
awesome_ctl/ui/src/components/agents/AgentDetails.tsx
awesome_ctl/ui/src/components/agents/AgentList.tsx
awesome_ctl/ui/src/components/alerts/AlertList.tsx
awesome_ctl/ui/src/components/checks/CheckDetails.tsx
awesome_ctl/ui/src/components/checks/CheckList.tsx
awesome_ctl/ui/src/components/checks/CreateCheckForm.tsx
awesome_ctl/ui/src/components/common/Charts/TimeSeriesChart.tsx
awesome_ctl/ui/src/components/common/Layout.tsx
awesome_ctl/ui/src/components/common/LoadingSpinner.tsx
awesome_ctl/ui/src/index.tsx
awesome_ctl/ui/src/pages/AlertsPage
awesome_ctl/ui/src/pages/ChecksPage
awesome_ctl/ui/src/pages/Dashboard.tsx
awesome_ctl/ui/src/pages/agentsPage.tsx
awesome_ctl/ui/src/pages/tsx
awesome_ctl/ui/tsconfig.json
awesome_ctl/utils.py
awesome_ctl-0.2.0.dist-info/LICENSE
awesome_ctl-0.2.0.dist-info/METADATA
awesome_ctl-0.2.0.dist-info/WHEEL
awesome_ctl-0.2.0.dist-info/entry_points.txt
awesome_ctl-0.2.0.dist-info/RECORD
