Metadata-Version: 2.1
Name: awesome-ctl
Version: 0.2.0
Summary: A comprehensive toolkit for CloudOps automation
Home-page: http://github.com/j-raghavan/awesome-ctl
License: MIT
Author: J-Raghavan
Author-email: mr.jayasimha@gmail.com
Requires-Python: >=3.10,<4.0
Classifier: License :: OSI Approved :: MIT License
Classifier: Programming Language :: Python :: 3
Classifier: Programming Language :: Python :: 3.10
Classifier: Programming Language :: Python :: 3.11
Classifier: Programming Language :: Python :: 3.12
Provides-Extra: kubernetes
Provides-Extra: openai
Requires-Dist: fastapi (>=0.98.0,<0.99.0)
Requires-Dist: kubernetes (>=26.1.0,<27.0.0) ; extra == "kubernetes"
Requires-Dist: openai (>=1.0.0,<2.0.0) ; extra == "openai"
Requires-Dist: pyfiglet (>=1.0.2,<2.0.0)
Requires-Dist: python-dateutil (>=2.9.0.post0,<3.0.0)
Requires-Dist: python-multipart (>=0.0.6,<0.0.7)
Requires-Dist: typer (>=0.9.0,<0.10.0)
Requires-Dist: uvicorn[standard] (>=0.23.2,<0.24.0)
Project-URL: Repository, http://github.com/j-raghavan/awesome-ctl
